libcps/PyCPS.py
libcps/__init__.py
PyClicksPerSecond-0.0.1.dist-info/METADATA
PyClicksPerSecond-0.0.1.dist-info/WHEEL
PyClicksPerSecond-0.0.1.dist-info/top_level.txt
PyClicksPerSecond-0.0.1.dist-info/RECORD
